chem_deg/__init__.py
chem_deg/degradation.py
chem_deg/main.py
chem_deg/util.py
chem_deg/assets/degradation_graph.png
chem_deg/assets/degradation_kinetics.png
chem_deg/kinetics/__init__.py
chem_deg/kinetics/graph.py
chem_deg/kinetics/halflife.py
chem_deg/kinetics/integration.py
chem_deg/reactions/__init__.py
chem_deg/reactions/base.py
chem_deg/reactions/reaction_classes.py
chem_deg/reactions/hydrolysis/__init__.py
chem_deg/reactions/hydrolysis/anhydride.py
chem_deg/reactions/hydrolysis/carbamate.py
chem_deg/reactions/hydrolysis/carbonate.py
chem_deg/reactions/hydrolysis/ester.py
chem_deg/reactions/hydrolysis/halogenated_aliphatic.py
chem_deg/reactions/hydrolysis/imide.py
chem_deg/reactions/hydrolysis/lactam.py
chem_deg/reactions/hydrolysis/lactone.py
chem_deg/reactions/hydrolysis/misc.py
chem_deg/reactions/hydrolysis/urea.py
chem_deg-0.2.2.dist-info/licenses/LICENSE
chem_deg-0.2.2.dist-info/METADATA
chem_deg-0.2.2.dist-info/WHEEL
chem_deg-0.2.2.dist-info/top_level.txt
chem_deg-0.2.2.dist-info/RECORD
