Metadata-Version: 2.4
Name: chem-deg
Version: 0.2.2
Summary: Chemical Degradation Simulation
Author: David Kuter
License-Expression: CC-BY-NC-4.0
Requires-Python: >=3.12
License-File: LICENSE
Requires-Dist: matplotlib>=3.10.1
Requires-Dist: networkx>=3.4.2
Requires-Dist: pandas>=2.2.3
Requires-Dist: rdkit>=2024.9.6
Requires-Dist: scipy>=1.15.2
Requires-Dist: seaborn>=0.13.2
Provides-Extra: dev
Requires-Dist: build; extra == "dev"
Requires-Dist: pytest>=7.0; extra == "dev"
Requires-Dist: pytest-cov>=4.0; extra == "dev"
Requires-Dist: ruff; extra == "dev"
Requires-Dist: twine; extra == "dev"
Dynamic: license-file
